Santa_IW/DBConnection.py
Santa_IW/DataRecording.py
Santa_IW/Discovery.py
Santa_IW/Flask/WebGUI.py
Santa_IW/Flask/__init__.py
Santa_IW/Flask/static/images/Images.md
Santa_IW/Flask/static/images/cheese-bell-1915234.svg
Santa_IW/Flask/static/images/cheese-bell-1915234_1280.png
Santa_IW/Flask/static/images/christmas-3827956.svg
Santa_IW/Flask/static/images/christmas-3827956_1280.png
Santa_IW/Flask/static/images/christmas-3835790.svg
Santa_IW/Flask/static/images/christmas-3835790_1280.png
Santa_IW/Flask/static/images/santa-1908028.svg
Santa_IW/Flask/static/images/santa-1908028_1280.png
Santa_IW/Flask/static/images/santa_circle_black.svg
Santa_IW/Flask/static/images/santa_circle_blue.svg
Santa_IW/Flask/static/images/santa_circle_gray.svg
Santa_IW/Flask/static/images/santa_circle_green.png
Santa_IW/Flask/static/images/santa_circle_green.svg
Santa_IW/Flask/static/images/santa_circle_purple.svg
Santa_IW/Flask/static/images/santa_circle_red.svg
Santa_IW/Flask/static/images/santa_circle_yellow.svg
Santa_IW/Flask/static/images/santa_outline_red.png
Santa_IW/Flask/static/images/santa_outline_red.svg
Santa_IW/Flask/static/images/wind-7658818.svg
Santa_IW/Flask/static/images/wind-7658818_1280.png
Santa_IW/Flask/templates/404_error.html.jinja
Santa_IW/Flask/templates/500_error.html.jinja
Santa_IW/Flask/templates/BoostrapBase.html.jinja
Santa_IW/Flask/templates/NavigationBar.html.jinja
Santa_IW/Flask/templates/OfflineBoostrapBase.html.jinja
Santa_IW/Flask/templates/control_page.html.jinja
Santa_IW/Flask/templates/focus_page.html.jinja
Santa_IW/Flask/templates/page_footer.html.jinja
Santa_IW/Flask/templates/table_analog_stats.html.jinja
Santa_IW/Flask/templates/table_config.html.jinja
Santa_IW/Flask/templates/table_discrete_stats.html.jinja
Santa_IW/Flask/templates/table_internal_status.html.jinja
Santa_IW/Flask/templates/table_subsystems.html.jinja
Santa_IW/INSTALL_CONFIG/PLUGIN_CONFIG/Hue.json_disabled
Santa_IW/INSTALL_CONFIG/TEMPLATES/Cockpit.json
santa_iw-0.9.0.dist-info/LICENSE.txt
santa_iw-0.9.0.dist-info/METADATA
santa_iw-0.9.0.dist-info/WHEEL
santa_iw-0.9.0.dist-info/entry_points.txt
santa_iw-0.9.0.dist-info/RECORD
