Metadata-Version: 2.1
Name: Santa_IW
Version: 0.9.0
Summary: Santa Is Watching: ZFS Aware Network Monitor
Author: Steve Goncalo
Author-email: steven@goncalo.us
Requires-Python: >=3.11,<4.0
Classifier: Development Status :: 4 - Beta
Classifier: Intended Audience :: Developers
Classifier: Intended Audience :: System Administrators
Classifier: License :: OSI Approved :: MIT License
Classifier: Natural Language :: English
Classifier: Operating System :: POSIX :: Linux
Classifier: Programming Language :: Python :: 3
Classifier: Programming Language :: Python :: 3.11
Classifier: Programming Language :: Python :: 3.12
Classifier: Topic :: System :: Monitoring
Classifier: Topic :: System :: Networking :: Monitoring :: Hardware Watchdog
Provides-Extra: doc
Requires-Dist: aiohue (>=4.7.1,<5.0.0)
Requires-Dist: flask (>=3.0.2,<3.1.0)
Requires-Dist: jinja2 (>=3.1.3,<3.2.0)
Requires-Dist: libsrg (>=5.2.3)
Requires-Dist: matplotlib (>=3.8.4,<4.0.0)
Requires-Dist: nltk (>=3.8.1,<3.9.0)
Requires-Dist: numpy (>=1.26.4,<2.0.0)
Requires-Dist: pandas (>=2.2.2,<3.0.0)
Requires-Dist: pathvalidate (>=3.2.0,<4.0.0)
Requires-Dist: requests (>=2.31.0,<2.32.0)
Requires-Dist: scipy (>=1.13.0,<2.0.0)
Requires-Dist: sphinx-rtd-theme[doc] (>=2.0.0,<3.0.0) ; extra == "doc"
Requires-Dist: sphinx[doc] (>=7.3.7,<8.0.0) ; extra == "doc"
Requires-Dist: sphinxcontrib-napoleon[doc] (>=0.7,<0.8) ; extra == "doc"
Requires-Dist: sqlalchemy (>=2.0.29,<3.0.0)
Requires-Dist: sympy (>=1.12,<2.0)
